html_compare/__init__.py
python_html_compare-0.1.0.dist-info/METADATA
python_html_compare-0.1.0.dist-info/WHEEL
python_html_compare-0.1.0.dist-info/RECORD
