Metadata-Version: 2.3
Name: python-html-compare
Version: 0.1.0
Summary: Python library for comparing HTML snippets
Author-email: tjk <tjkells@gmail.com>
Requires-Python: >=3.8
